csvtotrello/__init__.py
csvtotrello/bulk_import.py
csvtotrello-0.3.2.dist-info/METADATA
csvtotrello-0.3.2.dist-info/WHEEL
csvtotrello-0.3.2.dist-info/entry_points.txt
csvtotrello-0.3.2.dist-info/top_level.txt
csvtotrello-0.3.2.dist-info/RECORD
