Metadata-Version: 2.1
Name: csvtotrello
Version: 0.3.2
Summary: A package to bulk import csv backlog into Trello
Home-page: https://github.com/qeude/csvtotrello
Author: Quentin Eude
Author-email: quentineude@gmail.com
License: MIT
Platform: UNKNOWN
Requires-Dist: py-trello
